akriml/__init__.py
akriml/utils.py
akriml/sketch/__init__.py
akriml/sketch/fastsketch.py
akriml/sketch/sketch_utils.py
akriml-0.3.0.dist-info/LICENSE
akriml-0.3.0.dist-info/METADATA
akriml-0.3.0.dist-info/WHEEL
akriml-0.3.0.dist-info/top_level.txt
akriml-0.3.0.dist-info/RECORD
