Metadata-Version: 2.1
Name: akriml
Version: 0.3.0
Summary: ML methods for exploration and curation of large, high-dimensional datasets.
Author: Sabarish Vadarevu
Author-email: sabarish.vadarevu@akridata.ai
License: Apache License
Project-URL: homepage, https://akridata.ai
Project-URL: repository, https://github.com/akridata-ai/AkriML
Classifier: Programming Language :: Python :: 3
Classifier: Operating System :: OS Independent
Requires-Python: >=3.8
License-File: LICENSE
Requires-Dist: cython >=0.29.32
Requires-Dist: numpy >=1.23.4
Requires-Dist: scikit-learn >=1.1.3
Requires-Dist: scipy >=1.9.3
Provides-Extra: dev
Requires-Dist: flake8 ; extra == 'dev'
Requires-Dist: pre-commit ; extra == 'dev'
Requires-Dist: pytest ; extra == 'dev'
Requires-Dist: black ; extra == 'dev'
Requires-Dist: mypy ; extra == 'dev'
Requires-Dist: pylint ; extra == 'dev'
Requires-Dist: doctest ; extra == 'dev'
Requires-Dist: twine ; extra == 'dev'
Provides-Extra: test
Requires-Dist: pytest ; extra == 'test'
Requires-Dist: doctest ; extra == 'test'
